no_comment/__init__.py
no_comment/application/__init__.py
no_comment/application/use_cases/__init__.py
no_comment/application/use_cases/add_comment.py
no_comment/application/use_cases/create_stream.py
no_comment/application/use_cases/display_stream.py
no_comment/configuration/__init__.py
no_comment/configuration/cli.py
no_comment/configuration/wsgi.py
no_comment/domain/__init__.py
no_comment/domain/commenting/__init__.py
no_comment/domain/commenting/entities.py
no_comment/domain/commenting/exceptions.py
no_comment/domain/commenting/repositories.py
no_comment/domain/commenting/services.py
no_comment/domain/commenting/value_objects.py
no_comment/infrastructure/__init__.py
no_comment/infrastructure/click/__init__.py
no_comment/infrastructure/click/commands.py
no_comment/infrastructure/click/services.py
no_comment/infrastructure/flask/__init__.py
no_comment/infrastructure/flask/auth/__init__.py
no_comment/infrastructure/flask/ip/__init__.py
no_comment/infrastructure/flask/services.py
no_comment/infrastructure/flask/static/css/bulma@0.9.4.min.css
no_comment/infrastructure/flask/static/css/no-comment.css
no_comment/infrastructure/flask/static/img/add.svg
no_comment/infrastructure/flask/static/img/clock.svg
no_comment/infrastructure/flask/static/img/favicon.svg
no_comment/infrastructure/flask/static/img/feed.svg
no_comment/infrastructure/flask/static/img/filter-off.svg
no_comment/infrastructure/flask/static/img/filter.svg
no_comment/infrastructure/flask/static/img/logout.svg
no_comment/infrastructure/flask/static/img/manage.svg
no_comment/infrastructure/flask/static/img/search.svg
no_comment/infrastructure/flask/static/js/htmx@1.9.5.min.js
no_comment/infrastructure/flask/static/js/hyperscript@0.9.9.min.js
no_comment/infrastructure/flask/streams.py
no_comment/infrastructure/flask/totp/__init__.py
no_comment/infrastructure/flask/utils.py
no_comment/infrastructure/settings.py
no_comment/infrastructure/sqlalchemy/__init__.py
no_comment-0.2.0.dist-info/LICENSE
no_comment-0.2.0.dist-info/METADATA
no_comment-0.2.0.dist-info/WHEEL
no_comment-0.2.0.dist-info/entry_points.txt
no_comment-0.2.0.dist-info/RECORD
