Metadata-Version: 2.1
Name: no-comment
Version: 0.2.0
Summary: Comment any resource on the web!
License: AGPL-3.0-or-later
Author: Tanguy Le Carrour
Author-email: tanguy@bioneland.org
Requires-Python: >=3.9,<4.0
Classifier: License :: OSI Approved :: GNU Affero General Public License v3 or later (AGPLv3+)
Classifier: Programming Language :: Python :: 3
Classifier: Programming Language :: Python :: 3.9
Classifier: Programming Language :: Python :: 3.10
Classifier: Programming Language :: Python :: 3.11
Classifier: Programming Language :: Python :: 3.12
Provides-Extra: totp
Requires-Dist: Flask (>=3.0.2,<4.0.0)
Requires-Dist: SQLAlchemy (>=2.0.17,<3.0.0)
Requires-Dist: bl-seth (>=0.2.0,<0.3.0)
Requires-Dist: bl3d (>=0.4.1,<0.5.0)
Requires-Dist: click (>=8.1.3,<9.0.0)
Requires-Dist: jinja2 (>=3.1.1,<4.0.0)
Requires-Dist: jinja2-fragments (>=0.3.0,<0.4.0)
Requires-Dist: markdown (>=3.5,<4.0)
Requires-Dist: pyotp (>=2.8.0,<3.0.0) ; extra == "totp"
Requires-Dist: pypugjs (>=5.9.12,<6.0.0)
Requires-Dist: tzdata (>=2023.3,<2024.0)
